boggle_solver/__init__.py
boggle_solver/grid.py
boggle_solver/letter.py
boggle_solver/main.py
boggle_solver/words.txt
boggle_solver-1.1.dist-info/METADATA
boggle_solver-1.1.dist-info/WHEEL
boggle_solver-1.1.dist-info/top_level.txt
boggle_solver-1.1.dist-info/RECORD
